[
  {
    "uuid": "recd9ySSZXwzCQUnz",
    "id": 1,
    "name": "One-Handed Weapon",
    "items": [
      1,
      2,
      22,
      2045,
      2046,
      182,
      209,
      612,
      2153,
      16,
      12,
      35,
      2052,
      14,
      2037,
      2035,
      2004,
      628,
      639
    ],
    "subTypes": [
      1,
      2,
      3,
      5,
      6,
      23,
      28,
      27,
      30,
      38,
      41,
      22
    ],
    "recipes": [
      1,
      2,
      12,
      14,
      16,
      20
    ],
    "slots": [
      1,
      2
    ]
  },
  {
    "uuid": "rec8HrbZiHZRHL5wv",
    "id": 2,
    "name": "Two-Handed Weapon",
    "items": [
      49,
      11,
      2000,
      241,
      634,
      13,
      45,
      615,
      620,
      2023,
      2032,
      10,
      21,
      37,
      264,
      48,
      43,
      44,
      2054
    ],
    "subTypes": [
      4,
      8,
      7,
      18,
      19,
      20,
      21,
      34,
      35,
      52
    ],
    "recipes": [
      10,
      11,
      13,
      27
    ],
    "slots": [
      1
    ]
  },
  {
    "uuid": "recFMMTlS0zvqjMlK",
    "id": 3,
    "name": "Shield",
    "items": [
      15,
      33,
      36,
      2048,
      2007,
      2025
    ],
    "subTypes": [
      9,
      26,
      50,
      61
    ],
    "recipes": [
      15
    ],
    "slots": [
      2
    ]
  },
  {
    "uuid": "recnXv50rEytraEOH",
    "id": 4,
    "name": "Arrow",
    "items": [
      635
    ],
    "subTypes": [
      40
    ],
    "recipes": [],
    "slots": [
      2
    ]
  },
  {
    "uuid": "rec3uNSINwIOpffpA",
    "id": 5,
    "name": "Helm",
    "items": [
      3,
      19,
      30,
      39,
      54,
      617,
      622,
      625,
      627,
      637,
      2016,
      2049,
      2050,
      2002,
      2014,
      2031,
      2003,
      2024
    ],
    "subTypes": [
      10,
      51,
      54,
      55,
      60
    ],
    "recipes": [
      3,
      17
    ],
    "slots": [
      3
    ]
  },
  {
    "uuid": "recWK0kRyJFIIkz3n",
    "id": 20,
    "name": "Undercloth",
    "items": [],
    "subTypes": [],
    "recipes": [],
    "slots": [
      18
    ]
  },
  {
    "uuid": "recQqFOBQFbEuwfm1",
    "id": 7,
    "name": "Body Armor",
    "items": [
      6,
      31,
      34,
      53,
      222,
      47,
      303,
      624,
      629,
      632,
      638,
      2036,
      2039,
      2043,
      2030,
      2040,
      2042,
      2051,
      2041,
      2044,
      2012
    ],
    "subTypes": [
      13,
      45,
      46,
      47,
      48,
      59
    ],
    "recipes": [
      6
    ],
    "slots": [
      7
    ]
  },
  {
    "uuid": "recK9ncmHoCQk7Znr",
    "id": 50,
    "name": "Shoulder Armor",
    "items": [
      631
    ],
    "subTypes": [
      39
    ],
    "recipes": [],
    "slots": [
      11
    ]
  },
  {
    "uuid": "rechnKWMWcjdQhDNT",
    "id": 9,
    "name": "Glove",
    "items": [
      7,
      23,
      240,
      633,
      2021,
      2010,
      2009,
      2006
    ],
    "subTypes": [
      15,
      57,
      58
    ],
    "recipes": [
      7
    ],
    "slots": [
      9
    ]
  },
  {
    "uuid": "recEGo1W7iIYUUzAR",
    "id": 10,
    "name": "Belt",
    "items": [
      25,
      2034,
      2013,
      2026
    ],
    "subTypes": [
      25,
      42,
      43
    ],
    "recipes": [
      23
    ],
    "slots": [
      8
    ]
  },
  {
    "uuid": "recIu4Qk8wZ8t0nMw",
    "id": 11,
    "name": "Boot",
    "items": [
      5,
      55,
      38,
      46,
      616,
      640,
      2047,
      2008,
      2011,
      2022,
      2005,
      2038
    ],
    "subTypes": [
      12,
      49,
      56,
      44
    ],
    "recipes": [
      5
    ],
    "slots": [
      12
    ]
  },
  {
    "uuid": "recp3OrcyC5uktMMC",
    "id": 12,
    "name": "Ring",
    "items": [
      26,
      27,
      40,
      41,
      110,
      112,
      2154,
      618,
      2001,
      2015,
      2017,
      2018,
      2020,
      2028
    ],
    "subTypes": [
      14,
      53
    ],
    "recipes": [
      24,
      25
    ],
    "slots": [
      13,
      14,
      16
    ]
  },
  {
    "uuid": "recruATLbgOp8bejX",
    "id": 13,
    "name": "Amulet",
    "items": [
      28,
      109,
      29,
      2027,
      2029,
      2033
    ],
    "subTypes": [
      17
    ],
    "recipes": [
      26
    ],
    "slots": [
      5
    ]
  },
  {
    "uuid": "recuOFezVktVzh4kF",
    "id": 14,
    "name": "Trinket",
    "items": [
      32,
      1204,
      1200,
      1201,
      1203
    ],
    "subTypes": [
      29,
      31,
      32
    ],
    "recipes": [],
    "slots": [
      15,
      16,
      17
    ]
  },
  {
    "uuid": "recnT3DbhE36aMPjl",
    "id": 15,
    "name": "Consumable",
    "items": [
      1100,
      1211,
      1300
    ],
    "subTypes": [
      36
    ],
    "recipes": [],
    "slots": []
  },
  {
    "uuid": "recSD4r4pjrGH78Rv",
    "id": 16,
    "name": "Gem",
    "items": [],
    "subTypes": [],
    "recipes": [],
    "slots": []
  },
  {
    "uuid": "recpyWNNf3xDxZkyZ",
    "id": 17,
    "name": "Rune",
    "items": [],
    "subTypes": [],
    "recipes": [],
    "slots": []
  },
  {
    "uuid": "rec7uBEndGG3ZjlR7",
    "id": 18,
    "name": "Ingredient",
    "items": [
      4,
      3011,
      1205
    ],
    "subTypes": [
      11,
      63
    ],
    "recipes": [
      4
    ],
    "slots": []
  },
  {
    "uuid": "recps6qhyYB1vEU9h",
    "id": 19,
    "name": "Quest",
    "items": [],
    "subTypes": [],
    "recipes": [],
    "slots": []
  },
  {
    "uuid": "recBGTwFLondCYCss",
    "id": 6,
    "name": "Pet",
    "items": [
      3000,
      3001,
      3002,
      3003,
      3004,
      3005,
      3006,
      3007,
      3008
    ],
    "subTypes": [
      37
    ],
    "recipes": [],
    "slots": [
      4
    ]
  },
  {
    "uuid": "reciPqL4mM4mKS0td",
    "id": 21,
    "name": "Mount",
    "items": [],
    "subTypes": [],
    "recipes": [],
    "slots": [
      20
    ]
  },
  {
    "uuid": "reclvtK2pL3Jkosy0",
    "id": 22,
    "name": "Key",
    "items": [],
    "subTypes": [],
    "recipes": [],
    "slots": []
  },
  {
    "uuid": "recDHSR4xxDVbEnCe",
    "id": 23,
    "name": "Container",
    "items": [],
    "subTypes": [],
    "recipes": [],
    "slots": []
  },
  {
    "uuid": "recRVorGbqwnPLKrr",
    "id": 24,
    "name": "WristArmor",
    "items": [
      24,
      42,
      2019
    ],
    "subTypes": [
      24
    ],
    "recipes": [],
    "slots": [
      10
    ]
  },
  {
    "uuid": "reckXe1tEnAZVqdtt",
    "id": 25,
    "name": "Misc",
    "items": [
      1212,
      1202,
      1210
    ],
    "subTypes": [
      62,
      64
    ],
    "recipes": [],
    "slots": []
  },
  {
    "uuid": "recfgJF4tMpQyMmkU",
    "id": 8,
    "name": "Leg Armor",
    "items": [
      20,
      56,
      630
    ],
    "subTypes": [
      16
    ],
    "recipes": [],
    "slots": [
      6
    ]
  },
  {
    "uuid": "rec3oQ9npfEt4uvmY",
    "id": 25,
    "name": "Companion",
    "items": [],
    "subTypes": [],
    "recipes": [],
    "slots": [
      19
    ]
  },
  {
    "uuid": "recYA53sNfTgUDVlI",
    "id": 26,
    "name": "Cape",
    "items": [],
    "subTypes": [],
    "recipes": [],
    "slots": []
  }
]